ConnectWrapper/__init__.py
ConnectWrapper/Mobile/__init__.py
ConnectWrapper/Mobile/auth.py
ConnectWrapper/Mobile/grades.py
ConnectWrapper/Mobile/notices.py
ConnectWrapper-0.0.5.dist-info/LICENSE
ConnectWrapper-0.0.5.dist-info/METADATA
ConnectWrapper-0.0.5.dist-info/WHEEL
ConnectWrapper-0.0.5.dist-info/top_level.txt
ConnectWrapper-0.0.5.dist-info/RECORD
