Metadata-Version: 2.1
Name: ConnectWrapper
Version: 0.0.5
Summary: An easy-to-use wrapper for connect.det.wa.edu.au implemented in Python3
Home-page: https://github.com/Mitch0S/ConnectWrapper
Author: Mitch Naake
Author-email: mitchnaake@gmail.com
License: UNKNOWN
Project-URL: Bug Tracker, https://github.com/Mitch0S/ConnectWrapper/issues
Platform: UNKNOWN
Classifier: Programming Language :: Python :: 3
Classifier: License :: OSI Approved :: MIT License
Classifier: Operating System :: OS Independent
Requires-Python: >=3.6
License-File: LICENSE
